flowlet/__init__.py
flowlet/core.py
flowlet-0.1.0.dist-info/METADATA
flowlet-0.1.0.dist-info/WHEEL
flowlet-0.1.0.dist-info/top_level.txt
flowlet-0.1.0.dist-info/RECORD
