Metadata-Version: 2.4
Name: flowlet
Version: 0.1.0
Summary: A lightweight Python workflow engine with DAG nodes, async execution, and conditional branches.
Requires-Python: >=3.8
